mineager/UrlParser.py
mineager/__init__.py
mineager/data_types.py
mineager/globals.py
mineager/mineager.py
mineager/utils.py
mineager/cli/__init__.py
mineager/cli/cli_utils.py
mineager/cli/plugin/__init__.py
mineager/cli/plugin/commands.py
mineager/cli/plugin/manual_commands.py
mineager/cli/plugin/utils.py
mineager/config/Config.py
mineager/config/YamlConfig.py
mineager/config/__init__.py
mineager/plugins/GithubPlugin.py
mineager/plugins/JenkinsPlugin.py
mineager/plugins/Plugin.py
mineager/plugins/PluginLoader.py
mineager/plugins/SpigetPlugin.py
mineager/plugins/__init__.py
mineager-0.1.0.dist-info/LICENSE.md
mineager-0.1.0.dist-info/LICENSE_TEMPLATE.md
mineager-0.1.0.dist-info/METADATA
mineager-0.1.0.dist-info/WHEEL
mineager-0.1.0.dist-info/entry_points.txt
mineager-0.1.0.dist-info/top_level.txt
mineager-0.1.0.dist-info/RECORD
