Metadata-Version: 2.1
Name: mineager
Version: 0.1.0
Summary: Simple CLI tool to manage minecraft plugins on your server
Home-page: https://github.com/Prof-Bloodstone/
Author: Prof_Bloodstone
License: UNKNOWN
Platform: UNKNOWN
Classifier: Development Status :: 3 - Alpha
Classifier: Environment :: Console
Classifier: License :: OSI Approved :: GNU General Public License v3 (GPLv3)
Classifier: Natural Language :: English
Classifier: Topic :: Utilities
Classifier: Programming Language :: Python :: 3.6
Classifier: Programming Language :: Python :: 3.7
Classifier: Programming Language :: Python :: 3.8
Classifier: Programming Language :: Python :: 3.9
Requires-Python: >=3.6
Requires-Dist: Click
Requires-Dist: PyYAML
Requires-Dist: requests
